py_autotune/__init__.py
py_autotune/core.py
py_autotune/detection.py
py_autotune/shifting.py
py_autotune/utils.py
py_autotune-0.0.1.dist-info/licenses/LICENSE
py_autotune-0.0.1.dist-info/METADATA
py_autotune-0.0.1.dist-info/WHEEL
py_autotune-0.0.1.dist-info/top_level.txt
py_autotune-0.0.1.dist-info/RECORD
