Metadata-Version: 2.4
Name: py-autotune
Version: 0.0.1
Summary: Libreria Python per autotune su file audio.
Author-email: Gabriele Turelli <gabrieleturelli2004@gmail.com>
License-Expression: MIT
Requires-Python: >=3.8
License-File: LICENSE
Requires-Dist: numpy
Requires-Dist: scipy
Requires-Dist: soundfile
Dynamic: license-file
